server/__init__.py
server/__main__.py
server/cli.py
server/keep_api.py
keep_mcp-0.2.0.dist-info/METADATA
keep_mcp-0.2.0.dist-info/WHEEL
keep_mcp-0.2.0.dist-info/entry_points.txt
keep_mcp-0.2.0.dist-info/licenses/LICENSE
keep_mcp-0.2.0.dist-info/RECORD
