Metadata-Version: 2.4
Name: keep-mcp
Version: 0.2.0
Summary: MCP Server for Google Keep
Project-URL: Homepage, https://github.com/feuerdev/keep-mcp
Project-URL: Repository, https://github.com/feuerdev/keep-mcp
Author-email: Jannik Feuerhahn <jannik@feuer.dev>
License: MIT License
License-File: LICENSE
Classifier: Development Status :: 4 - Beta
Classifier: Environment :: Console
Classifier: Intended Audience :: End Users/Desktop
Classifier: License :: OSI Approved :: MIT License
Classifier: Programming Language :: Python :: 3
Classifier: Programming Language :: Python :: 3.10
Classifier: Topic :: Utilities
Requires-Python: >=3.10
Requires-Dist: gkeepapi>=0.16.0
Requires-Dist: mcp[cli]
